<?xml version="1.0" encoding="UTF-8" standalone="yes" ?>
<program>
  <header>
    <applicationBuildName></applicationBuildName>
    <applicationBuildNumber>0</applicationBuildNumber>
    <applicationBuildType>release</applicationBuildType>
    <applicationName>NewCatroid</applicationName>
    <applicationVersion>2.1.1b2</applicationVersion>
    <catrobatLanguageVersion>1.17</catrobatLanguageVersion>
    <customResolution>false</customResolution>
    <dateTimeUpload></dateTimeUpload>
    <description></description>
    <deviceName>M2003J15SC</deviceName>
    <gitRemoteUrl></gitRemoteUrl>
    <isCastProject>false</isCastProject>
    <landscapeMode>true</landscapeMode>
    <listeningLanguageTag></listeningLanguageTag>
    <mediaLicense></mediaLicense>
    <notesAndCredits></notesAndCredits>
    <physicsHeightArea>2.0</physicsHeightArea>
    <physicsWidthArea>3.0</physicsWidthArea>
    <platform>Android</platform>
    <platformVersion>31</platformVersion>
    <programLicense></programLicense>
    <programName>TV FX OS 1.0</programName>
    <remixOf></remixOf>
    <scenesEnabled>true</scenesEnabled>
    <screenHeight>1080</screenHeight>
    <screenMode>STRETCH</screenMode>
    <screenWidth>2110</screenWidth>
    <tags></tags>
    <url></url>
    <userHandle></userHandle>
  </header>
  <settings/>
  <scenes>
    <scene sceneId="7744f40f-cda9-4da3-b9be-3ca47dfd3782">
      <name>Сцена</name>
      <objectList>
        <object type="Sprite" spriteId="480865a2-3e63-4294-95f2-50930c00eace" name="Фон">
          <lookList/>
          <soundList/>
          <scriptList/>
          <nfcTagList/>
          <userVariables/>
          <userLists/>
          <userDefinedBrickList/>
        </object>
      </objectList>
    </scene>
  </scenes>
  <programVariableList/>
  <programListOfLists/>
  <programMultiplayerVariableList/>
</program>